keios_protocol_common/__init__.py
keios_protocol_common-0.1.2.dist-info/WHEEL
keios_protocol_common-0.1.2.dist-info/METADATA
keios_protocol_common-0.1.2.dist-info/RECORD
